{
    "collaborators": [
        "amgadge",
        "chnegiz",
        "ywang",
        "vijetmuley",
        "cjkarasi"
    ],
    "created_at": "2018-10-10 16:42:56",
    "edges": [
        {
            "ports": [
                {
                    "input": "mathematical_exploration",
                    "type": "csv"
                }
            ],
            "source": "clean_data.csv",
            "target": "mathematical_data_exploration.R"
        },
        {
            "ports": [
                {
                    "input": "regression_model",
                    "type": "csv"
                }
            ],
            "source": "clean_data.csv",
            "target": "regression_models.R"
        },
        {
            "ports": [
                {
                    "input": "classified_models",
                    "type": "csv"
                }
            ],
            "source": "clean_data.csv",
            "target": "classification_models.R"
        },
        {
            "ports": [
                {
                    "input": "raw_data",
                    "type": "csv"
                }
            ],
            "source": "satisfactionSurvey.csv",
            "target": "cleaning_2.R"
        },
        {
            "ports": [
                {
                    "output": "df",
                    "type": "csv"
                }
            ],
            "source": "cleaning_2.R",
            "target": "clean_data.csv"
        },
        {
            "ports": [
                {
                    "input": "df",
                    "type": "csv"
                }
            ],
            "source": "clean_data.csv",
            "target": "ExplorationA.R"
        },
        {
            "ports": [
                {
                    "output": "plot1",
                    "type": "png"
                }
            ],
            "source": "ExplorationA.R",
            "target": "visualization_graphs_1.png"
        },
        {
            "ports": [
                {
                    "output": "plot3",
                    "type": "png"
                }
            ],
            "source": "ExplorationA.R",
            "target": "GenderSatisfactions.png"
        },
        {
            "ports": [
                {
                    "input": "clean_data",
                    "type": "csv"
                }
            ],
            "source": "clean_data.csv",
            "target": "ExplorationCK.R"
        },
        {
            "ports": [
                {
                    "output": "plot2",
                    "type": "png"
                }
            ],
            "source": "ExplorationA.R",
            "target": "AgeSatisfaction.png"
        },
        {
            "ports": [
                {
                    "output": "plot4",
                    "type": "png"
                }
            ],
            "source": "ExplorationA.R",
            "target": "PriceSensitivitySatisfaction.png"
        },
        {
            "ports": [
                {
                    "output": "plot5",
                    "type": "png"
                }
            ],
            "source": "ExplorationA.R",
            "target": "YearOfFirstFlightSatisfaction.png"
        },
        {
            "ports": [
                {
                    "input": "clean_data.csv",
                    "type": "csv"
                }
            ],
            "source": "clean_data.csv",
            "target": "piechart.R"
        },
        {
            "ports": [
                {
                    "output": "barplot1",
                    "type": "png"
                }
            ],
            "source": "mathematical_data_exploration.R",
            "target": "TypeofTravel_stackedbarchart.png"
        },
        {
            "ports": [
                {
                    "output": "gender_PC",
                    "type": "png"
                }
            ],
            "source": "piechart.R",
            "target": "gender_piechart.png"
        },
        {
            "ports": [
                {
                    "output": "AS_PC",
                    "type": "png"
                }
            ],
            "source": "piechart.R",
            "target": "airline_status_piechart.png"
        },
        {
            "ports": [
                {
                    "output": "TT_PC",
                    "type": "png"
                }
            ],
            "source": "piechart.R",
            "target": "traveltype_piechart.png"
        },
        {
            "ports": [
                {
                    "output": "CT_PC",
                    "type": "png"
                }
            ],
            "source": "piechart.R",
            "target": "class_type_piechart.png"
        },
        {
            "ports": [
                {
                    "output": "AD_PC",
                    "type": "png"
                }
            ],
            "source": "piechart.R",
            "target": "arrival_delay_piechart.png"
        },
        {
            "ports": [
                {
                    "output": "eatingScatterPlot",
                    "type": "png"
                }
            ],
            "source": "ExplorationCK.R",
            "target": "eatingAndDrinkingScater.png"
        },
        {
            "ports": [
                {
                    "output": "delayScatterPlot",
                    "type": "png"
                }
            ],
            "source": "ExplorationCK.R",
            "target": "departureDelayScatter.png"
        },
        {
            "ports": [
                {
                    "output": "monthBarChart",
                    "type": "png"
                }
            ],
            "source": "ExplorationCK.R",
            "target": "monthBarChart.png"
        },
        {
            "ports": [
                {
                    "output": "classBarChart",
                    "type": "png"
                }
            ],
            "source": "ExplorationCK.R",
            "target": "classBarChart.png"
        },
        {
            "ports": [
                {
                    "output": "scheduledBarChart",
                    "type": "png"
                }
            ],
            "source": "ExplorationCK.R",
            "target": "scheduledBarChart.png"
        },
        {
            "ports": [
                {
                    "output": "histScheduledDepartureHour",
                    "type": "png"
                }
            ],
            "source": "ExplorationCK.R",
            "target": "HistScheduledDepartureHour.png"
        },
        {
            "ports": [
                {
                    "output": "histEatingAndDrinking",
                    "type": "png"
                }
            ],
            "source": "ExplorationCK.R",
            "target": "histEatingAndDrinking.png"
        },
        {
            "ports": [
                {
                    "output": "ggplot1",
                    "type": "png"
                }
            ],
            "source": "mathematical_data_exploration.R",
            "target": "passenger_number_of_flights.png.png"
        },
        {
            "ports": [
                {
                    "output": "ggplot2",
                    "type": "png"
                }
            ],
            "source": "mathematical_data_exploration.R",
            "target": "Number_of_other_Airlines.png"
        },
        {
            "ports": [
                {
                    "output": "ggplot3",
                    "type": "png"
                }
            ],
            "source": "mathematical_data_exploration.R",
            "target": "No_of_other_Loyalty_Cards.png"
        },
        {
            "ports": [
                {
                    "output": "ggplot0",
                    "type": "png"
                }
            ],
            "source": "mathematical_data_exploration.R",
            "target": "ShoppingAmount_scatterplot1.png.png"
        },
        {
            "ports": [
                {
                    "output": "link",
                    "type": "png"
                }
            ],
            "source": "maps.R",
            "target": "map1.png"
        },
        {
            "ports": [
                {
                    "output": "map1",
                    "type": "png"
                }
            ],
            "source": "maps.R",
            "target": "map2.png"
        },
        {
            "ports": [
                {
                    "output": "map3",
                    "type": "png"
                }
            ],
            "source": "maps.R",
            "target": "map3.png"
        },
        {
            "ports": [
                {
                    "output": "map44",
                    "type": "png"
                }
            ],
            "source": "maps.R",
            "target": "map4.png"
        },
        {
            "ports": [
                {
                    "output": "map55",
                    "type": "png"
                }
            ],
            "source": "maps.R",
            "target": "map5.png"
        },
        {
            "ports": [
                {
                    "input": "df",
                    "type": "csv"
                }
            ],
            "source": "clean_data.csv",
            "target": "maps.R"
        }
    ],
    "nodes": [
        {
            "name": "satisfactionSurvey.csv"
        },
        {
            "name": "clean_data.csv"
        },
        {
            "name": "visualization_graphs_1.png"
        },
        {
            "name": "visualization_graphs_2.png"
        },
        {
            "name": "YearOfFirstFlightSatisfaction.png"
        },
        {
            "assigned_to": "cjkarasi",
            "desc": "-Kernel SVM\r\n-XG Boost\r\n-clustering (k-means)",
            "name": "classification_models.R",
            "task_status": "proposed"
        },
        {
            "name": "final_visualization.png"
        },
        {
            "assigned_to": "amgadge",
            "desc": "Encoding categorical variables,\r\nseprating date into months and inserting new coloumn as month,\r\nremoving erroneuous rows/ outliers",
            "name": "cleaning_2.R",
            "task_status": "validating"
        },
        {
            "name": "ageVsSatisfact.png"
        },
        {
            "name": "GenderSatisfactions.png"
        },
        {
            "name": "AgeSatisfaction.png"
        },
        {
            "name": "PriceSensitivitySatisfaction.png"
        },
        {
            "assigned_to": "amgadge",
            "desc": "-visualize final results of data analysis",
            "name": "final_visualization.R",
            "task_status": "not started"
        },
        {
            "assigned_to": "vijetmuley",
            "desc": "-multiple regression model (step-wise)\r\n-polynomial regressions\r\n-random forest\r\n-Logistics regressions",
            "name": "regression_models.R",
            "task_status": "not started"
        },
        {
            "assigned_to": "cjkarasi",
            "desc": "",
            "name": "bargraph.R",
            "task_status": "not started"
        },
        {
            "assigned_to": "not assigned",
            "desc": "Eating and drinking visualizations",
            "name": "EatingAndDrinking.R",
            "task_status": "not started"
        },
        {
            "assigned_to": "chnegiz",
            "desc": "",
            "name": "piechart.R",
            "task_status": "in progress"
        },
        {
            "assigned_to": "amgadge",
            "desc": "Exploration and visualizing Airline Status, Age, Gender, Price sensitivity and years of flight",
            "name": "ExplorationA.R",
            "task_status": "in progress"
        },
        {
            "name": "TypeofTravel_stackedbarchart.png"
        },
        {
            "name": "gender_piechart.png"
        },
        {
            "name": "airline_status_piechart.png"
        },
        {
            "name": "traveltype_piechart.png"
        },
        {
            "name": "class_type_piechart.png"
        },
        {
            "name": "arrival_delay_piechart.png"
        },
        {
            "name": "eatingAndDrinkingScater.png"
        },
        {
            "name": "departureDelayScatter.png"
        },
        {
            "name": "monthBarChart.png"
        },
        {
            "name": "classBarChart.png"
        },
        {
            "name": "scheduledBarChart.png"
        },
        {
            "name": "HistScheduledDepartureHour.png"
        },
        {
            "assigned_to": "cjkarasi",
            "desc": "Scheduled departure hour, departure delay in minutes, eating and drinking at the airport, class, day of month ",
            "name": "ExplorationCK.R",
            "task_status": "in progress"
        },
        {
            "name": "histEatingAndDrinking.png"
        },
        {
            "name": "passenger_number_of_flights.png.png"
        },
        {
            "name": "Number_of_other_Airlines.png"
        },
        {
            "name": "No_of_other_Loyalty_Cards.png"
        },
        {
            "name": "map1.png"
        },
        {
            "name": "map2.png"
        },
        {
            "name": "map3.png"
        },
        {
            "name": "map4.png"
        },
        {
            "name": "map5.png"
        },
        {
            "name": "ShoppingAmount_scatterplot1.png.png"
        },
        {
            "assigned_to": "cjkarasi",
            "desc": "",
            "name": "maps.R",
            "task_status": "in progress"
        },
        {
            "assigned_to": "ywang",
            "desc": "-descriptive statistics\r\n-correlation tables",
            "name": "mathematical_data_exploration.R",
            "task_status": "in progress"
        },
        {
            "assigned_to": "amgadge",
            "desc": "modelling the data using  Random Forest Algorithm",
            "name": "RandomForest.R",
            "task_status": "in progress"
        },
        {
            "name": "flightdelayPC.png"
        }
    ],
    "updated_at": "2018-11-15 17:08:33",
    "url": "https://github.com/fall2018-saltz/ist687_project_team_3"
}